<?xml version="1.0" encoding="UTF-8"?>
<!DOCTYPE blogic-io PUBLIC "-//NTTDATA//DTD TERASOLUNA for Spring blogic-io 1.0//JA"
                           "../dtd/blogic-io.dtd">
<!-- Generated by TERASOLUNA IDE -->
<blogic-io>
    <action path="/PR_E_EXP_S01InitBL">
        <blogic-params bean-name="nttdm.bsys.e_exp.dto.PR_E_EXP_S01InitInput">
            <set-property blogic-property="uvo" property="USER_VALUE_OBJECT" source="session"/>
            <set-property blogic-property="row" property="row" source="form"/>
            <set-property blogic-property="startIndex" property="startIndex" source="form"/>
            <set-property blogic-property="closingMonth" property="closingMonth" source="form"/>
            <set-property blogic-property="closingYear" property="closingYear" source="form"/>
            <!-- Add #146 Start -->
            <set-property blogic-property="customerTypeDispFlg" property="customerTypeDispFlg" source="form"/>
            <set-property blogic-property="customerType" property="customerType" source="form"/>
            <!-- Add #146 End-->
            <set-property blogic-property="typeFlg" property="typeFlg" source="form"/>
        </blogic-params>
        <blogic-result>
            <set-property blogic-property="closingMonth" dest="form" property="closingMonth"/>
            <set-property blogic-property="closingYear" dest="form" property="closingYear"/>
            <!-- Add #146 Start -->
            <set-property blogic-property="customerTypeDispFlg" dest="form" property="customerTypeDispFlg"/>
            <set-property blogic-property="customerType" dest="form" property="customerType"/>
            <!-- Add #146 End-->
            <set-property blogic-property="totalRow" dest="form" property="totalRow"/>
            <set-property blogic-property="row" dest="form" property="row"/>
            <set-property blogic-property="startIndex" dest="form" property="startIndex"/>
            <set-property blogic-property="listHistories" dest="form" property="listHistories"/>
        </blogic-result>
    </action>
    <action path="/PR_E_EXP_S01ExecuteBL">
        <blogic-params bean-name="nttdm.bsys.e_exp.dto.PR_E_EXP_S01ExecuteInput">
            <set-property blogic-property="uvo" property="USER_VALUE_OBJECT" source="session"/>
            <set-property blogic-property="closingMonth" property="closingMonth" source="form"/>
            <set-property blogic-property="closingYear" property="closingYear" source="form"/>
            <!-- Add #146 Start -->
            <set-property blogic-property="customerTypeDispFlg" property="customerTypeDispFlg" source="form"/>
            <set-property blogic-property="customerType" property="customerType" source="form"/>
            <!-- Add #146 End-->
        </blogic-params>
        <blogic-result>
            <set-property blogic-property="closingMonth" dest="form" property="closingMonth"/>
            <set-property blogic-property="closingYear" dest="form" property="closingYear"/>
            <!-- Add #146 Start -->
            <set-property blogic-property="customerTypeDispFlg" dest="form" property="customerTypeDispFlg"/>
            <set-property blogic-property="customerType" dest="form" property="customerType"/>
            <!-- Add #146 End-->
            <set-property blogic-property="typeFlg" dest="form" property="typeFlg"/>
        </blogic-result>
    </action>
    <action path="/PR_E_EXP_S01ExecuteCheckErrorBL">
        <blogic-params bean-name="nttdm.bsys.e_exp.dto.PR_E_EXP_S01ExecuteCheckErrorInput">
            <set-property blogic-property="uvo" property="USER_VALUE_OBJECT" source="session"/>
            <set-property blogic-property="closingMonth" property="closingMonth" source="form"/>
            <set-property blogic-property="closingYear" property="closingYear" source="form"/>
        </blogic-params>
        <blogic-result>
            <set-property blogic-property="closingMonth" dest="form" property="closingMonth"/>
            <set-property blogic-property="closingYear" dest="form" property="closingYear"/>
            <set-property blogic-property="typeFlg" dest="form" property="typeFlg"/>
        </blogic-result>
    </action>
    <action path="/RP_E_EXP_S01DownloadBL">
        <blogic-params bean-name="nttdm.bsys.e_exp.dto.RP_E_EXP_S01DownloadInput">
            <set-property blogic-property="uvo" property="USER_VALUE_OBJECT" source="session"/>
            <set-property blogic-property="idBatch" property="idBatch" source="form"/>
            <set-property blogic-property="filename" property="filename" source="form"/>
        </blogic-params>
    </action>
    <action path="/RP_E_EXP_S01LogInitBL">
        <blogic-params bean-name="nttdm.bsys.e_exp.dto.RP_E_EXP_S01LogInitInput">
            <set-property blogic-property="uvo" property="USER_VALUE_OBJECT" source="session"/>
            <set-property blogic-property="idBatch" property="idBatch" source="form"/>
        </blogic-params>
        <blogic-result>
            <set-property blogic-property="logsList" dest="form" property="logsList"/>
        </blogic-result>
    </action>
</blogic-io>
